afet/__init__.py
afet/core/__init__.py
afet/core/advanced_explainability.py
afet/core/advanced_fairness_metrics.py
afet/core/advanced_visualizations.py
afet/core/bias_mitigation.py
afet/core/config.py
afet/core/explainability.py
afet/core/fairness_metrics.py
afet/core/fairness_mitigation.py
afet/core/logging_setup.py
afet/core/model_comparison.py
afet/core/metrics/__init__.py
afet/core/mitigation/__init__.py
afet/core/visualization/__init__.py
afet/dashboard/api.py
afet/dashboard/app.py
afet/dashboard/components/__init__.py
afet/dashboard/pages/__init__.py
afet/datasets/hiring_dataset.py
afet/datasets/medical_dataset.py
afet/datasets/synthetic_loan_dataset.py
afet/datasets/loaders/__init__.py
afet/datasets/synthetic/__init__.py
afet/examples/__init__.py
afet/examples/finance/__init__.py
afet/examples/finance/credit_scoring.py
afet/examples/healthcare/__init__.py
afet/examples/healthcare/patient_readmission.py
afet/examples/hiring/__init__.py
afet/examples/hiring/hiring_analysis.py
afet/examples/tutorials/__init__.py
afet/models/__init__.py
afet/models/model_registry.py
afet/models/pytorch/__init__.py
afet/models/sklearn/__init__.py
afet/models/tensorflow/__init__.py
afet/tests/__init__.py
afet/tests/test_fairness_metrics.py
afet/tests/test_model_comparison.py
afet/tests/integration/__init__.py
afet/tests/unit/__init__.py
afet/viz/__init__.py
afet/viz/interactive_plots.py
ai_fairness_toolkit-0.1.1.dist-info/licenses/LICENSE
ai_fairness_toolkit-0.1.1.dist-info/METADATA
ai_fairness_toolkit-0.1.1.dist-info/WHEEL
ai_fairness_toolkit-0.1.1.dist-info/top_level.txt
ai_fairness_toolkit-0.1.1.dist-info/RECORD
