Metadata-Version: 2.4
Name: ai-fairness-toolkit
Version: 0.1.1
Summary: A comprehensive toolkit for evaluating and improving AI model fairness and explainability
Author-email: Taimoor Khan <taimoorkhaniajaznabi2@gmail.com>
Project-URL: Homepage, https://github.com/TaimoorKhan10/AI-Fairness-Explainability-Toolkit
Project-URL: Documentation, https://ai-fairness-toolkit.readthedocs.io/
Project-URL: Repository, https://github.com/TaimoorKhan10/AI-Fairness-Explainability-Toolkit
Project-URL: Issues, https://github.com/TaimoorKhan10/AI-Fairness-Explainability-Toolkit/issues
Project-URL: Changelog, https://github.com/TaimoorKhan10/AI-Fairness-Explainability-Toolkit/blob/main/CHANGELOG.md
Project-URL: Source, https://github.com/TaimoorKhan10/AI-Fairness-Explainability-Toolkit
Classifier: Development Status :: 3 - Alpha
Classifier: Intended Audience :: Science/Research
Classifier: Intended Audience :: Developers
Classifier: License :: OSI Approved :: MIT License
Classifier: Programming Language :: Python :: 3.8
Classifier: Programming Language :: Python :: 3.9
Classifier: Programming Language :: Python :: 3.10
Classifier: Topic :: Scientific/Engineering
Classifier: Topic :: Scientific/Engineering :: Artificial Intelligence
Classifier: Topic :: Software Development :: Libraries :: Python Modules
Requires-Python: >=3.8
License-File: LICENSE
Requires-Dist: numpy>=1.20.0
Requires-Dist: pandas>=1.3.0
Requires-Dist: scikit-learn>=1.0.0
Requires-Dist: plotly>=5.0.0
Requires-Dist: matplotlib>=3.5.0
Requires-Dist: seaborn>=0.11.0
Requires-Dist: tqdm>=4.0.0
Requires-Dist: scipy>=1.7.0
Requires-Dist: joblib>=1.1.0
Requires-Dist: requests>=2.26.0
Requires-Dist: pyyaml>=6.0.0
Provides-Extra: dev
Requires-Dist: pytest>=7.0.0; extra == "dev"
Requires-Dist: pytest-cov>=3.0.0; extra == "dev"
Requires-Dist: black>=22.1.0; extra == "dev"
Requires-Dist: isort>=5.10.0; extra == "dev"
Requires-Dist: flake8>=4.0.0; extra == "dev"
Requires-Dist: mypy>=0.931; extra == "dev"
Requires-Dist: pre-commit>=2.17.0; extra == "dev"
Provides-Extra: docs
Requires-Dist: sphinx>=4.4.0; extra == "docs"
Requires-Dist: sphinx-rtd-theme>=1.0.0; extra == "docs"
Requires-Dist: nbsphinx>=0.8.8; extra == "docs"
Requires-Dist: myst-parser>=0.17.0; extra == "docs"
Dynamic: license-file
